MANIFEST.in
README.rst
setup.py
bin/findyourday_find
findyourday/__init__.py
findyourday/command_line.py
findyourday/functions.py
findyourday/inputexceptions.py
findyourday.egg-info/PKG-INFO
findyourday.egg-info/SOURCES.txt
findyourday.egg-info/dependency_links.txt
findyourday.egg-info/entry_points.txt
findyourday.egg-info/not-zip-safe
findyourday.egg-info/top_level.txt