Metadata-Version: 1.1
Name: findyourday
Version: 0.2
Summary: Finds the day for a given date
Home-page: http://github.com/nimnathw/findyourday
Author: Nimnath Withanachchi
Author-email: nimnathw@gmail.com
License: MIT
Keywords: find the day of the week for a date
Platform: UNKNOWN
Classifier: Development Status :: 3 - Alpha
Classifier: License :: Freeware
Classifier: Programming Language :: Python :: 2.7
Classifier: Natural Language :: English
